{"expireTime":9007200884406519000,"key":"90997bfcc1920b33c098fd1b96a955c8","val":{"name":"IMAGE_PROCESSING","inputPaths":["/Users/Bozinovski/Desktop/Home/minimal-portfolio/content/images/html.png"],"outputDir":"/Users/Bozinovski/Desktop/Home/minimal-portfolio/public/static/8e61c34461e66889c8bf71895d241a8a","args":{"isLazy":false,"operations":[{"outputPath":"03b0d/html.webp","args":{"height":100,"width":100,"cropFocus":17,"toFormat":"webp","quality":80,"fit":"cover"}},{"outputPath":"46280/html.webp","args":{"height":200,"width":200,"cropFocus":17,"toFormat":"webp","quality":80,"fit":"cover"}},{"outputPath":"dc0d0/html.webp","args":{"height":400,"width":400,"cropFocus":17,"toFormat":"webp","quality":80,"fit":"cover"}}],"pluginOptions":{"base64Width":20,"forceBase64Format":"","useMozJpeg":false,"stripMetadata":true,"lazyImageGeneration":true,"defaultQuality":50,"failOnError":true,"plugins":[]}}}}